skfair/__init__.py
skfair/common.py
skfair/datasets.py
skfair/data/arrests.zip
skfair/preprocessing/__init__.py
skfair/preprocessing/informationfilter.py
tests/__init__.py
tests/conftest.py
scikit_fairness-0.0.1.dist-info/METADATA
scikit_fairness-0.0.1.dist-info/WHEEL
scikit_fairness-0.0.1.dist-info/top_level.txt
scikit_fairness-0.0.1.dist-info/RECORD
