Metadata-Version: 2.1
Name: scikit-fairness
Version: 0.0.1
Summary: a collection of utilities to make algorithms more fair
Home-page: https://scikit-lego.readthedocs.io/en/latest/
Author: Vincent D. Warmerdam & Matthijs Brouns
License: UNKNOWN
Platform: UNKNOWN
Classifier: Intended Audience :: Developers
Classifier: Intended Audience :: Science/Research
Classifier: Programming Language :: Python :: 3
Classifier: Programming Language :: Python :: 3.6
Classifier: Programming Language :: Python :: 3.7
Classifier: License :: OSI Approved :: MIT License
Classifier: Topic :: Scientific/Engineering
Classifier: Topic :: Scientific/Engineering :: Artificial Intelligence
Requires-Dist: numpy (>=1.16.0)
Requires-Dist: scipy (>=1.2.0)
Requires-Dist: scikit-learn (>=0.20.2)
Requires-Dist: pandas (>=0.23.4)
Requires-Dist: patsy (>=0.5.1)
Requires-Dist: autograd (>=1.2)
Requires-Dist: cvxpy (>=1.0.24)
Requires-Dist: Deprecated (>=1.2.6)
Provides-Extra: dev
Requires-Dist: sphinx (>=1.8.5) ; extra == 'dev'
Requires-Dist: sphinx-rtd-theme (>=0.4.3) ; extra == 'dev'
Requires-Dist: nbsphinx (>=0.4.2) ; extra == 'dev'
Requires-Dist: ghp-import (>=0.5.5) ; extra == 'dev'
Requires-Dist: flake8 (>=3.6.0) ; extra == 'dev'
Requires-Dist: nbval (>=0.9.1) ; extra == 'dev'
Requires-Dist: pytest (>=4.0.2) ; extra == 'dev'
Requires-Dist: black (>=19.3b0) ; extra == 'dev'
Requires-Dist: pytest-cov (>=2.6.1) ; extra == 'dev'
Requires-Dist: pytest-mock (>=1.6.3) ; extra == 'dev'
Requires-Dist: pre-commit (>=1.18.3) ; extra == 'dev'
Requires-Dist: matplotlib (>=3.0.2) ; extra == 'dev'
Requires-Dist: plotnine (>=0.5.1) ; extra == 'dev'
Requires-Dist: jupyter (>=1.0.0) ; extra == 'dev'
Requires-Dist: jupyterlab (>=0.35.4) ; extra == 'dev'
Provides-Extra: docs
Requires-Dist: sphinx (>=1.8.5) ; extra == 'docs'
Requires-Dist: sphinx-rtd-theme (>=0.4.3) ; extra == 'docs'
Requires-Dist: nbsphinx (>=0.4.2) ; extra == 'docs'
Requires-Dist: ghp-import (>=0.5.5) ; extra == 'docs'
Provides-Extra: test
Requires-Dist: flake8 (>=3.6.0) ; extra == 'test'
Requires-Dist: nbval (>=0.9.1) ; extra == 'test'
Requires-Dist: pytest (>=4.0.2) ; extra == 'test'
Requires-Dist: black (>=19.3b0) ; extra == 'test'
Requires-Dist: pytest-cov (>=2.6.1) ; extra == 'test'
Requires-Dist: pytest-mock (>=1.6.3) ; extra == 'test'
Requires-Dist: pre-commit (>=1.18.3) ; extra == 'test'
